odd_airflow/__init__.py
odd_airflow/dag.py
odd_airflow/settings.py
odd_airflow/utils.py
odd_airflow/extractors/__init__.py
odd_airflow/extractors/biquery.py
odd_airflow/extractors/postgres.py
odd_airflow/oddrn/__init__.py
odd_airflow/oddrn/airflow.py
odd_airflow/oddrn/postgres.py
odd_airflow-0.0.7.dist-info/METADATA
odd_airflow-0.0.7.dist-info/WHEEL
odd_airflow-0.0.7.dist-info/top_level.txt
odd_airflow-0.0.7.dist-info/RECORD
